odoo/addons/intercompany_shared_contact/README.rst
odoo/addons/intercompany_shared_contact/__init__.py
odoo/addons/intercompany_shared_contact/__manifest__.py
odoo/addons/intercompany_shared_contact/i18n/es.po
odoo/addons/intercompany_shared_contact/i18n/intercompany_shared_contact.pot
odoo/addons/intercompany_shared_contact/i18n/it.po
odoo/addons/intercompany_shared_contact/models/__init__.py
odoo/addons/intercompany_shared_contact/models/res_company.py
odoo/addons/intercompany_shared_contact/models/res_partner.py
odoo/addons/intercompany_shared_contact/models/res_users.py
odoo/addons/intercompany_shared_contact/readme/CONTRIBUTORS.rst
odoo/addons/intercompany_shared_contact/readme/DESCRIPTION.rst
odoo/addons/intercompany_shared_contact/readme/ROADMAP.rst
odoo/addons/intercompany_shared_contact/security/ir_rule.xml
odoo/addons/intercompany_shared_contact/static/description/icon.png
odoo/addons/intercompany_shared_contact/static/description/index.html
odoo/addons/intercompany_shared_contact/tests/__init__.py
odoo/addons/intercompany_shared_contact/tests/models.py
odoo/addons/intercompany_shared_contact/tests/test_shared_contacts.py
odoo14_addon_intercompany_shared_contact-14.0.1.1.3.dist-info/METADATA
odoo14_addon_intercompany_shared_contact-14.0.1.1.3.dist-info/WHEEL
odoo14_addon_intercompany_shared_contact-14.0.1.1.3.dist-info/top_level.txt
odoo14_addon_intercompany_shared_contact-14.0.1.1.3.dist-info/RECORD
