Metadata-Version: 2.1
Name: odoo14-addon-intercompany-shared-contact
Version: 14.0.1.1.3
Summary: User of each company are contact of a company partner. All child address of a company are automatically shared
Home-page: https://github.com/OCA/multi-company
Author: Odoo Community Association (OCA), Akretion
Author-email: support@odoo-community.org
License: AGPL-3
Platform: UNKNOWN
Classifier: Programming Language :: Python
Classifier: Framework :: Odoo
Classifier: Framework :: Odoo :: 14.0
Classifier: License :: OSI Approved :: GNU Affero General Public License v3
Requires-Python: >=3.6
Requires-Dist: odoo <14.1dev,>=14.0a
